LICENSE
MANIFEST.in
README.md
requirements.txt
setup.cfg
setup.py
norns/__about__.py
norns/__init__.py
norns/cfg.py
norns/exceptions.py
norns.egg-info/PKG-INFO
norns.egg-info/SOURCES.txt
norns.egg-info/dependency_links.txt
norns.egg-info/requires.txt
norns.egg-info/top_level.txt